techmanpy/__init__.py
techmanpy/exceptions.py
techmanpy/clients/__init__.py
techmanpy/clients/stateful_client.py
techmanpy/clients/stateless_client.py
techmanpy/clients/techman_client.py
techmanpy/clients/tmsct_client.py
techmanpy/clients/tmsta_client.py
techmanpy/clients/tmsvr_client.py
techmanpy/packets/__init__.py
techmanpy/packets/cperr_packet.py
techmanpy/packets/stateful_packet.py
techmanpy/packets/stateless_packet.py
techmanpy/packets/tmsct_packet.py
techmanpy/packets/tmsta_packet.py
techmanpy/packets/tmsvr_packet.py
techmanpy-1.2.dist-info/LICENSE
techmanpy-1.2.dist-info/METADATA
techmanpy-1.2.dist-info/WHEEL
techmanpy-1.2.dist-info/top_level.txt
techmanpy-1.2.dist-info/RECORD
