Metadata-Version: 2.1
Name: techmanpy
Version: 1.2
Summary: Communication driver for Techman robots
Home-page: https://github.com/jvdtoorn/techmanpy
Author: Jules van der Toorn
Author-email: julesvandertoorn@gmail.com
License: MIT
Project-URL: Source, https://github.com/jvdtoorn/techmanpy
Keywords: techman driver manipulator robotics
Platform: UNKNOWN
Classifier: Programming Language :: Python :: 3
Classifier: Programming Language :: Python :: 3.8
Classifier: License :: OSI Approved :: MIT License
Classifier: Operating System :: POSIX :: Linux
Classifier: Intended Audience :: Science/Research
Classifier: Natural Language :: English
Requires-Python: ~=3.8
